MANIFEST.in
README.md
setup.cfg
setup.py
dexseq_prepare_annotation2/__init__.py
dexseq_prepare_annotation2.egg-info/PKG-INFO
dexseq_prepare_annotation2.egg-info/SOURCES.txt
dexseq_prepare_annotation2.egg-info/dependency_links.txt
dexseq_prepare_annotation2.egg-info/entry_points.txt
dexseq_prepare_annotation2.egg-info/requires.txt
dexseq_prepare_annotation2.egg-info/top_level.txt