Metadata-Version: 1.1
Name: dexseq-prepare-annotation2
Version: 1.0.0
Summary: Subread_to_DEXSeq python package
Home-page: https://github.com/jvrakor/Subread_to_DEXSeq
Author: UNKNOWN
Author-email: UNKNOWN
License: UNKNOWN
Download-URL: https://github.com/jvrakor/Subread_to_DEXSeq/tarball/v1.0.0
Keywords: bioinformatics,dexseq,featurecounts,annotation
Platform: UNKNOWN
